avkapi/__init__.py
avkapi/vk.py
avkapi/dispatcher/__init__.py
avkapi/dispatcher/dispatcher.py
avkapi/dispatcher/filters.py
avkapi/dispatcher/handler.py
avkapi/dispatcher/middlewares.py
avkapi/dispatcher/storage.py
avkapi/dispatcher/webhook.py
avkapi/methods/__init__.py
avkapi/methods/base.py
avkapi/methods/messages.py
avkapi/schema/__init__.py
avkapi/types/__init__.py
avkapi/types/action.py
avkapi/types/attachment.py
avkapi/types/base.py
avkapi/types/event.py
avkapi/types/exceptions.py
avkapi/types/fields.py
avkapi/types/geo.py
avkapi/types/message.py
avkapi/types/photo.py
avkapi/utils/__init__.py
avkapi/utils/context.py
avkapi/utils/deprecated.py
avkapi/utils/executor.py
avkapi/utils/helper.py
avkapi/utils/json.py
avkapi/utils/payload.py
tests/__init__.py
aVKapi-0.1.2.dist-info/LICENSE
aVKapi-0.1.2.dist-info/METADATA
aVKapi-0.1.2.dist-info/WHEEL
aVKapi-0.1.2.dist-info/top_level.txt
aVKapi-0.1.2.dist-info/RECORD
