Metadata-Version: 2.1
Name: aVKapi
Version: 0.1.2
Summary: Python asyncio VK.com API library
Home-page: https://github.com/aiogram/aVKapi
Author: aiogram team
Author-email: 1282524@gmail.com
License: UNKNOWN
Platform: UNKNOWN
Classifier: Development Status :: 3 - Alpha
Classifier: Environment :: Console
Classifier: Framework :: AsyncIO
Classifier: License :: OSI Approved :: MIT License
Classifier: Natural Language :: English
Classifier: Operating System :: OS Independent
Classifier: Intended Audience :: Developers
Classifier: Programming Language :: Python :: 3.6
